<T3DataStructure>
    <meta>
        <langChildren>0</langChildren>
        <langDisable>1</langDisable>
    </meta>
    <sheets>
        <sDEF>
            <ROOT>
                <TCEforms>
                    <sheetTitle>LLL:EXT:pb_social/Resources/Private/Language/locallang_db.xlf:flexform.tab.general.caption</sheetTitle>
                </TCEforms>
                <type>array</type>
                <el>
                    <settings.sysLogThisPlugin>
                        <TCEforms>
                            <label>LLL:EXT:pb_social/Resources/Private/Language/locallang_db.xlf:flexform.tab.general.sysLogThisPlugin</label>
                            <config>
                                <type>check</type>
                            </config>
                        </TCEforms>
                    </settings.sysLogThisPlugin>

                    <settings.refreshTimeInMin>
                        <TCEforms>
                            <label>LLL:EXT:pb_social/Resources/Private/Language/locallang_db.xlf:flexform.tab.general.updatingFeeds</label>
                            <config>
                                <type>input</type>
                            </config>
                        </TCEforms>
                    </settings.refreshTimeInMin>
                    <settings.feedRequestLimit>
                        <TCEforms>
                            <label>LLL:EXT:pb_social/Resources/Private/Language/locallang_db.xlf:flexform.tab.general.requestLimit</label>
                            <config>
                                <type>input</type>
                            </config>
                        </TCEforms>
                    </settings.feedRequestLimit>
                    <settings.onlyWithPicture>
                        <TCEforms>
                            <label>LLL:EXT:pb_social/Resources/Private/Language/locallang_db.xlf:flexform.tab.general.showOnlyImages</label>
                            <config>
                                <type>check</type>
                            </config>
                        </TCEforms>
                    </settings.onlyWithPicture>
                    <settings.textTrimLength>
                        <TCEforms>
                            <label>LLL:EXT:pb_social/Resources/Private/Language/locallang_db.xlf:flexform.tab.general.trimText</label>
                            <config>
                                <type>input</type>
                                <default>130</default>
                            </config>
                        </TCEforms>
                    </settings.textTrimLength>
                </el>
            </ROOT>
        </sDEF>
        <display_facebook>
            <ROOT>
                <TCEforms>
                    <sheetTitle>LLL:EXT:pb_social/Resources/Private/Language/locallang_db.xlf:flexform.tab.facebook.caption</sheetTitle>
                </TCEforms>
                <type>array</type>
                <el>
                    <settings.facebookEnabled>
                        <TCEforms>
                            <label>LLL:EXT:pb_social/Resources/Private/Language/locallang_db.xlf:flexform.tab.facebook.active</label>

                            <config>
                                <type>check</type>
                            </config>
                        </TCEforms>
                    </settings.facebookEnabled>
                    <settings.facebookFullPicture>
                        <TCEforms>
                            <label>LLL:EXT:pb_social/Resources/Private/Language/locallang_db.xlf:flexform.tab.facebook.fullpicture</label>

                            <config>
                                <type>check</type>
                            </config>
                        </TCEforms>
                    </settings.facebookFullPicture>
                    <settings.facebookPageID>
                        <TCEforms>
                            <label>LLL:EXT:pb_social/Resources/Private/Language/locallang_db.xlf:flexform.tab.facebook.facebookPageID</label>
                            <config>
                                <type>input</type>
                            </config>
                        </TCEforms>
                    </settings.facebookPageID>
                    <settings.facebookEdge>
                        <TCEforms>
                        <label>LLL:EXT:pb_social/Resources/Private/Language/locallang_db.xlf:flexform.tab.facebook.edge</label>
                        <config>
                          <type>radio</type>
                          <items type="array">
                            <numIndex index="0" type="array">
                              <numIndex index="0">LLL:EXT:pb_social/Resources/Private/Language/locallang_db.xlf:flexform.tab.facebook.edge.feed</numIndex>
                              <numIndex index="1">feed</numIndex>
                            </numIndex>
                            <numIndex index="1" type="array">
                              <numIndex index="0">LLL:EXT:pb_social/Resources/Private/Language/locallang_db.xlf:flexform.tab.facebook.edge.posts</numIndex>
                              <numIndex index="1">posts</numIndex>
                            </numIndex>
                              <numIndex index="2" type="array">
                                  <numIndex index="0">LLL:EXT:pb_social/Resources/Private/Language/locallang_db.xlf:flexform.tab.facebook.edge.tagged</numIndex>
                                  <numIndex index="1">tagged</numIndex>
                              </numIndex>
                          </items>
                          <default>feed</default>
                        </config>
                        </TCEforms>
                    </settings.facebookEdge>
                    <settings.facebookPluginKeyfieldEnabled>
                        <TCEforms>
                            <label>LLL:EXT:pb_social/Resources/Private/Language/locallang_db.xlf:flexform.tab.facebook.facebookPluginKeyfieldEnabled</label>
                            <onChange>reload</onChange>
                            <config>
                                <type>check</type>
                            </config>
                        </TCEforms>
                    </settings.facebookPluginKeyfieldEnabled>
                    <settings.facebookApiId>
                        <TCEforms>
                            <label>LLL:EXT:pb_social/Resources/Private/Language/locallang_extconf.xlf:facebook.api.id</label>
                            <displayCond>FIELD:settings.facebookPluginKeyfieldEnabled:=:1</displayCond>
                            <config>
                                <type>input</type>
                            </config>
                        </TCEforms>
                    </settings.facebookApiId>
                    <settings.facebookApiSecret>
                        <TCEforms>
                            <label>LLL:EXT:pb_social/Resources/Private/Language/locallang_extconf.xlf:facebook.api.secret</label>
                            <displayCond>FIELD:settings.facebookPluginKeyfieldEnabled:=:1</displayCond>
                            <config>
                                <type>input</type>
                            </config>
                        </TCEforms>
                    </settings.facebookApiSecret>
                    <settings.facebookPageAccessToken>
                        <TCEforms>
                            <label>LLL:EXT:pb_social/Resources/Private/Language/locallang_extconf.xlf:facebook.api.pageaccesstoken</label>
                            <displayCond>FIELD:settings.facebookPluginKeyfieldEnabled:=:1</displayCond>
                            <config>
                                <type>input</type>
                            </config>
                        </TCEforms>
                    </settings.facebookPageAccessToken>

                </el>
            </ROOT>
        </display_facebook>
        <display_instagram>
            <ROOT>
            <TCEforms>
                <sheetTitle>LLL:EXT:pb_social/Resources/Private/Language/locallang_db.xlf:flexform.tab.instagram.caption</sheetTitle>
            </TCEforms>
            <type>array</type>
            <el>
                <settings.instagramEnabled>
                    <TCEforms>
                        <label>LLL:EXT:pb_social/Resources/Private/Language/locallang_db.xlf:flexform.tab.instagram.active</label>

                        <config>
                            <type>check</type>
                        </config>
                    </TCEforms>
                </settings.instagramEnabled>
                <settings.instagramSearchIds>
                    <TCEforms>
                        <label>LLL:EXT:pb_social/Resources/Private/Language/locallang_db.xlf:flexform.tab.instagram.searchID</label>
                        <config>
                            <type>input</type>
                        </config>
                    </TCEforms>
                </settings.instagramSearchIds>
                <settings.instagramHashTag>
                    <TCEforms>
                        <label>LLL:EXT:pb_social/Resources/Private/Language/locallang_db.xlf:flexform.tab.instagram.hashtag</label>
                        <config>
                            <type>input</type>
                        </config>
                    </TCEforms>
                </settings.instagramHashTag>
                <settings.instagramPostFilter>
                    <TCEforms>
                        <label>LLL:EXT:pb_social/Resources/Private/Language/locallang_db.xlf:flexform.tab.instagram.postfilter</label>
                        <config>
                            <type>check</type>
                        </config>
                    </TCEforms>
                </settings.instagramPostFilter>

                <settings.instagramPluginKeyfieldEnabled>
                    <TCEforms>
                        <label>LLL:EXT:pb_social/Resources/Private/Language/locallang_db.xlf:flexform.tab.instagram.instagramPluginKeyfieldEnabled</label>
                        <onChange>reload</onChange>
                        <config>
                            <type>check</type>
                        </config>
                    </TCEforms>
                </settings.instagramPluginKeyfieldEnabled>
                <settings.instagramClientId>
                    <TCEforms>
                        <label>LLL:EXT:pb_social/Resources/Private/Language/locallang_extconf.xlf:instagram.client.id</label>
                        <displayCond>FIELD:settings.instagramPluginKeyfieldEnabled:=:1</displayCond>
                        <config>
                            <type>input</type>
                        </config>
                    </TCEforms>
                </settings.instagramClientId>
                <settings.instagramClientSecret>
                    <TCEforms>
                        <label>LLL:EXT:pb_social/Resources/Private/Language/locallang_extconf.xlf:instagram.client.secret</label>
                        <displayCond>FIELD:settings.instagramPluginKeyfieldEnabled:=:1</displayCond>
                        <config>
                            <type>input</type>
                        </config>
                    </TCEforms>
                </settings.instagramClientSecret>
                 <settings.instagramClientCallback>
                    <TCEforms>
                        <label>LLL:EXT:pb_social/Resources/Private/Language/locallang_extconf.xlf:instagram.client.callback</label>
                        <displayCond>FIELD:settings.instagramPluginKeyfieldEnabled:=:1</displayCond>
                        <config>
                            <type>input</type>
                        </config>
                    </TCEforms>
                </settings.instagramClientCallback>
                <settings.instagramClientAccess_code>
                    <TCEforms>
                        <label>LLL:EXT:pb_social/Resources/Private/Language/locallang_extconf.xlf:instagram.client.access_code</label>
                        <displayCond>FIELD:settings.instagramPluginKeyfieldEnabled:=:1</displayCond>
                        <config>
                            <type>input</type>
                        </config>
                    </TCEforms>
                </settings.instagramClientAccess_code>
                <settings.instagramClientAaccess_token>
                    <TCEforms>
                        <label>LLL:EXT:pb_social/Resources/Private/Language/locallang_extconf.xlf:instagram.client.access_token</label>
                        <displayCond>FIELD:settings.instagramPluginKeyfieldEnabled:=:1</displayCond>
                        <config>
                            <type>input</type>
                        </config>
                    </TCEforms>
                </settings.instagramClientAaccess_token>
            </el>
        </ROOT>
        </display_instagram>
        <display_linkedin>
            <ROOT>
                <TCEforms>
                    <sheetTitle>LLL:EXT:pb_social/Resources/Private/Language/locallang_db.xlf:flexform.tab.linkedin.caption</sheetTitle>
                </TCEforms>
                <type>array</type>
                <el>
                    <settings.linkedinEnabled>
                        <TCEforms>
                            <label>LLL:EXT:pb_social/Resources/Private/Language/locallang_db.xlf:flexform.tab.linkedin.active</label>

                            <config>
                                <type>check</type>
                            </config>
                        </TCEforms>
                    </settings.linkedinEnabled>
                    <settings.linkedinCompanyIds>
                        <TCEforms>
                            <label>LLL:EXT:pb_social/Resources/Private/Language/locallang_db.xlf:flexform.tab.linkedin.companyIds</label>
                            <config>
                                <type>input</type>
                            </config>
                        </TCEforms>
                    </settings.linkedinCompanyIds>
                    <settings.linkedinFilterChoice>
                        <TCEforms>
                            <label>LLL:EXT:pb_social/Resources/Private/Language/locallang_db.xlf:flexform.tab.linkedin.linkedinFilterChoice</label>
                            <config>
                                <type>radio</type>
                                <items type="array">
                                    <numIndex index="0" type="array">
                                        <numIndex index="0">LLL:EXT:pb_social/Resources/Private/Language/locallang_db.xlf:flexform.tab.linkedin.linkedinFilterChoiceNone</numIndex>
                                        <numIndex index="1"></numIndex>
                                    </numIndex>
                                    <numIndex index="1" type="array">
                                        <numIndex index="0">LLL:EXT:pb_social/Resources/Private/Language/locallang_db.xlf:flexform.tab.linkedin.jobPostings</numIndex>
                                        <numIndex index="1">job-posting</numIndex>
                                    </numIndex>
                                    <numIndex index="2" type="array">
                                        <numIndex index="0">LLL:EXT:pb_social/Resources/Private/Language/locallang_db.xlf:flexform.tab.linkedin.newProducts</numIndex>
                                        <numIndex index="1">new-product</numIndex>
                                    </numIndex>
                                    <numIndex index="3" type="array">
                                        <numIndex index="0">LLL:EXT:pb_social/Resources/Private/Language/locallang_db.xlf:flexform.tab.linkedin.statusUpdates</numIndex>
                                        <numIndex index="1">status-update</numIndex>
                                    </numIndex>
                                </items>
                            </config>
                        </TCEforms>
                    </settings.linkedinFilterChoice>
                    
                    <settings.linkedinPluginKeyfieldEnabled>
                        <TCEforms>
                            <label>LLL:EXT:pb_social/Resources/Private/Language/locallang_db.xlf:flexform.tab.linkedin.linkedinPluginKeyfieldEnabled</label>
                            <onChange>reload</onChange>
                            <config>
                                <type>check</type>
                            </config>
                        </TCEforms>
                    </settings.linkedinPluginKeyfieldEnabled>
                    <settings.linkedinClientKey>
                        <TCEforms>
                            <label>LLL:EXT:pb_social/Resources/Private/Language/locallang_extconf.xlf:linkedin.client.key</label>
                            <displayCond>FIELD:settings.linkedinPluginKeyfieldEnabled:=:1</displayCond>
                            <config>
                                <type>input</type>
                            </config>
                        </TCEforms>
                    </settings.linkedinClientKey>
                    <settings.linkedinClientSecret>
                        <TCEforms>
                            <label>LLL:EXT:pb_social/Resources/Private/Language/locallang_extconf.xlf:linkedin.client.secret</label>
                            <displayCond>FIELD:settings.linkedinPluginKeyfieldEnabled:=:1</displayCond>
                            <config>
                                <type>input</type>
                            </config>
                        </TCEforms>
                    </settings.linkedinClientSecret>
                    <settings.linkedinClientCallbackUrl>
                        <TCEforms>
                            <label>LLL:EXT:pb_social/Resources/Private/Language/locallang_extconf.xlf:linkedin.client.callback_url</label>
                            <displayCond>FIELD:settings.linkedinPluginKeyfieldEnabled:=:1</displayCond>
                            <config>
                                <type>input</type>
                            </config>
                        </TCEforms>
                    </settings.linkedinClientCallbackUrl>
                    <settings.linkedinAccessToken>
                        <TCEforms>
                            <label>LLL:EXT:pb_social/Resources/Private/Language/locallang_extconf.xlf:linkedin.access_token</label>
                            <displayCond>FIELD:settings.linkedinPluginKeyfieldEnabled:=:1</displayCond>
                            <config>
                                <type>input</type>
                            </config>
                        </TCEforms>
                    </settings.linkedinAccessToken>

                    
                </el>
            </ROOT>
        </display_linkedin>
        <display_pinterest>
            <ROOT>
                <TCEforms>
                    <sheetTitle>LLL:EXT:pb_social/Resources/Private/Language/locallang_db.xlf:flexform.tab.pinterest.caption</sheetTitle>
                </TCEforms>
                <type>array</type>
                <el>
                    <settings.pinterestEnabled>
                        <TCEforms>
                            <label>LLL:EXT:pb_social/Resources/Private/Language/locallang_db.xlf:flexform.tab.pinterest.active</label>
                            <config>
                                <type>check</type>
                            </config>
                        </TCEforms>
                    </settings.pinterestEnabled>
                    <settings.username>
                        <TCEforms>
                            <label>LLL:EXT:pb_social/Resources/Private/Language/locallang_db.xlf:flexform.tab.pinterest.username</label>
                            <config>
                                <type>input</type>
                            </config>
                        </TCEforms>
                    </settings.username>
                    <settings.boardname>
                        <TCEforms>
                            <label>LLL:EXT:pb_social/Resources/Private/Language/locallang_db.xlf:flexform.tab.pinterest.boardname</label>
                            <config>
                                <type>input</type>
                            </config>
                        </TCEforms>
                    </settings.boardname>

                    <settings.pinterestPluginKeyfieldEnabled>
                        <TCEforms>
                            <label>LLL:EXT:pb_social/Resources/Private/Language/locallang_db.xlf:flexform.tab.pinterest.pinterestPluginKeyfieldEnabled</label>
                            <onChange>reload</onChange>
                            <config>
                                <type>check</type>
                            </config>
                        </TCEforms>
                    </settings.pinterestPluginKeyfieldEnabled>
                    <settings.pinterestAppId>
                        <TCEforms>
                            <label>LLL:EXT:pb_social/Resources/Private/Language/locallang_extconf.xlf:pinterest.app.id</label>
                            <displayCond>FIELD:settings.pinterestPluginKeyfieldEnabled:=:1</displayCond>
                            <config>
                                <type>input</type>
                            </config>
                        </TCEforms>
                    </settings.pinterestAppId>
                     <settings.pinterestAppSsecret>
                        <TCEforms>
                            <label>LLL:EXT:pb_social/Resources/Private/Language/locallang_extconf.xlf:pinterest.app.secret</label>
                            <displayCond>FIELD:settings.pinterestPluginKeyfieldEnabled:=:1</displayCond>
                            <config>
                                <type>input</type>
                            </config>
                        </TCEforms>
                    </settings.pinterestAppSsecret>
                     <settings.pinterestAppCode>
                        <TCEforms>
                            <label>LLL:EXT:pb_social/Resources/Private/Language/locallang_extconf.xlf:pinterest.app.code</label>
                            <displayCond>FIELD:settings.pinterestPluginKeyfieldEnabled:=:1</displayCond>
                            <config>
                                <type>input</type>
                            </config>
                        </TCEforms>
                    </settings.pinterestAppCode>

                </el>
            </ROOT>
        </display_pinterest>
        <display_twitter>
            <ROOT>
                <TCEforms>
                    <sheetTitle>LLL:EXT:pb_social/Resources/Private/Language/locallang_db.xlf:flexform.tab.twitter.caption</sheetTitle>
                </TCEforms>
                <type>array</type>
                <el>
                    <settings.twitterEnabled>
                        <TCEforms>
                            <label>LLL:EXT:pb_social/Resources/Private/Language/locallang_db.xlf:flexform.tab.twitter.active</label>

                            <config>
                                <type>check</type>
                            </config>
                        </TCEforms>
                    </settings.twitterEnabled>
                    <settings.twitterHideRetweets>
                        <TCEforms>
                            <label>LLL:EXT:pb_social/Resources/Private/Language/locallang_db.xlf:flexform.tab.twitter.hideRetweets</label>

                            <config>
                                <type>check</type>
                            </config>
                        </TCEforms>
                    </settings.twitterHideRetweets>
                    <settings.twitterShowOnlyImages>
                        <TCEforms>
                            <label>LLL:EXT:pb_social/Resources/Private/Language/locallang_db.xlf:flexform.tab.twitter.showOnlyImages</label>
                            <config>
                                <type>check</type>
                            </config>
                        </TCEforms>
                    </settings.twitterShowOnlyImages>
                    <settings.twitterSearchFieldValues>
                        <TCEforms>
                            <label>LLL:EXT:pb_social/Resources/Private/Language/locallang_db.xlf:flexform.tab.twitter.searchID</label>
                            <config>
                                <type>input</type>
                            </config>
                        </TCEforms>
                    </settings.twitterSearchFieldValues>
                    <settings.twitterProfilePosts>
                        <TCEforms>
                            <label>LLL:EXT:pb_social/Resources/Private/Language/locallang_db.xlf:flexform.tab.twitter.profilePosts</label>
                            <config>
                                <type>input</type>
                            </config>
                        </TCEforms>
                    </settings.twitterProfilePosts>
                    <settings.twitterLanguage>
                        <TCEforms>
                            <label>LLL:EXT:pb_social/Resources/Private/Language/locallang_db.xlf:flexform.tab.twitter.language</label>
                            <config>
                                <type>input</type>
                            </config>
                        </TCEforms>
                    </settings.twitterLanguage>
                    <settings.twitterGeoCode>
                        <TCEforms>
                            <label>LLL:EXT:pb_social/Resources/Private/Language/locallang_db.xlf:flexform.tab.twitter.geocode</label>
                            <config>
                                <type>input</type>
                            </config>
                        </TCEforms>
                    </settings.twitterGeoCode>
                    <settings.twitterHTTPS>
                        <TCEforms>
                            <label>LLL:EXT:pb_social/Resources/Private/Language/locallang_db.xlf:flexform.tab.twitter.https</label>
                            <config>
                                <type>check</type>
                            </config>
                        </TCEforms>
                    </settings.twitterHTTPS>

                    <settings.twitterPluginKeyfieldEnabled>
                        <TCEforms>
                            <label>LLL:EXT:pb_social/Resources/Private/Language/locallang_db.xlf:flexform.tab.twitter.twitterPluginKeyfieldEnabled</label>
                            <onChange>reload</onChange>
                            <config>
                                <type>check</type>
                            </config>
                        </TCEforms>
                    </settings.twitterPluginKeyfieldEnabled>
                    <settings.twitterConsumerKey>
                        <TCEforms>
                            <label>LLL:EXT:pb_social/Resources/Private/Language/locallang_extconf.xlf:twitter.consumer.key</label>
                            <displayCond>FIELD:settings.twitterPluginKeyfieldEnabled:=:1</displayCond>
                            <config>
                                <type>input</type>
                            </config>
                        </TCEforms>
                    </settings.twitterConsumerKey>
                    <settings.twitterConsumerSecret>
                        <TCEforms>
                            <label>LLL:EXT:pb_social/Resources/Private/Language/locallang_extconf.xlf:twitter.consumer.secret</label>
                            <displayCond>FIELD:settings.twitterPluginKeyfieldEnabled:=:1</displayCond>
                            <config>
                                <type>input</type>
                            </config>
                        </TCEforms>
                    </settings.twitterConsumerSecret>
                    <settings.twitterOauthAccessToken>
                        <TCEforms>
                            <label>LLL:EXT:pb_social/Resources/Private/Language/locallang_extconf.xlf:twitter.oauth.access.token</label>
                            <displayCond>FIELD:settings.twitterPluginKeyfieldEnabled:=:1</displayCond>
                            <config>
                                <type>input</type>
                            </config>
                        </TCEforms>
                    </settings.twitterOauthAccessToken>
                    <settings.twitterOauthAccessTokenSecret>
                        <TCEforms>
                            <label>LLL:EXT:pb_social/Resources/Private/Language/locallang_extconf.xlf:twitter.oauth.access.token_secret</label>
                            <displayCond>FIELD:settings.twitterPluginKeyfieldEnabled:=:1</displayCond>
                            <config>
                                <type>input</type>
                            </config>
                        </TCEforms>
                    </settings.twitterOauthAccessTokenSecret>
                </el>
            </ROOT>
        </display_twitter>
        <display_youtube>
            <ROOT>
                <TCEforms>
                    <sheetTitle>LLL:EXT:pb_social/Resources/Private/Language/locallang_db.xlf:flexform.tab.youtube.caption</sheetTitle>
                </TCEforms>
                <type>array</type>
                <el>
                    <settings.youtubeEnabled>
                        <TCEforms>
                            <label>LLL:EXT:pb_social/Resources/Private/Language/locallang_db.xlf:flexform.tab.youtube.active</label>
                            <config>
                                <type>check</type>
                            </config>
                        </TCEforms>
                    </settings.youtubeEnabled>
                    <settings.youtubeSearch>
                        <TCEforms>
                            <label>LLL:EXT:pb_social/Resources/Private/Language/locallang_db.xlf:flexform.tab.youtube.searchword</label>
                            <config>
                                <type>input</type>
                            </config>
                        </TCEforms>
                    </settings.youtubeSearch>
                    <settings.youtubePlaylist>
                        <TCEforms>
                            <label>LLL:EXT:pb_social/Resources/Private/Language/locallang_db.xlf:flexform.tab.youtube.playlist</label>
                            <config>
                                <type>input</type>
                            </config>
                        </TCEforms>
                    </settings.youtubePlaylist>
                    <settings.youtubeChannel>
                        <TCEforms>
                            <label>LLL:EXT:pb_social/Resources/Private/Language/locallang_db.xlf:flexform.tab.youtube.channel</label>
                            <config>
                                <type>input</type>
                            </config>
                        </TCEforms>
                    </settings.youtubeChannel>
                    <settings.youtubeLanguage>
                        <TCEforms>
                            <label>LLL:EXT:pb_social/Resources/Private/Language/locallang_db.xlf:flexform.tab.youtube.lang</label>
                            <config>
                                <type>input</type>
                            </config>
                        </TCEforms>
                    </settings.youtubeLanguage>
                    <settings.youtubeType>
                        <TCEforms>
                            <label>LLL:EXT:pb_social/Resources/Private/Language/locallang_db.xlf:flexform.tab.youtube.type</label>
                            <config>
                                <type>input</type>
                            </config>
                        </TCEforms>
                    </settings.youtubeType>
                    <settings.youtubeOrder>
                        <TCEforms>
                            <label>LLL:EXT:pb_social/Resources/Private/Language/locallang_db.xlf:flexform.tab.youtube.order</label>
                            <config>
                                <type>select</type>
                                <items type="array">
                                    <numIndex index="0" type="array">
                                        <numIndex index="0">LLL:EXT:pb_social/Resources/Private/Language/locallang_db.xlf:flexform.tab.youtube.order.relevance</numIndex>
                                        <numIndex index="1">relevance</numIndex>
                                    </numIndex>
                                    <numIndex index="1" type="array">
                                        <numIndex index="0">LLL:EXT:pb_social/Resources/Private/Language/locallang_db.xlf:flexform.tab.youtube.order.date</numIndex>
                                        <numIndex index="1">date</numIndex>
                                    </numIndex>
                                    <numIndex index="2" type="array">
                                        <numIndex index="0">LLL:EXT:pb_social/Resources/Private/Language/locallang_db.xlf:flexform.tab.youtube.order.viewCount</numIndex>
                                        <numIndex index="1">viewCount</numIndex>
                                    </numIndex>
                                    <numIndex index="3" type="array">
                                        <numIndex index="0">LLL:EXT:pb_social/Resources/Private/Language/locallang_db.xlf:flexform.tab.youtube.order.videoCount</numIndex>
                                        <numIndex index="1">videoCount</numIndex>
                                    </numIndex>
                                    <numIndex index="4" type="array">
                                        <numIndex index="0">LLL:EXT:pb_social/Resources/Private/Language/locallang_db.xlf:flexform.tab.youtube.order.title</numIndex>
                                        <numIndex index="1">title</numIndex>
                                    </numIndex>
                                    <numIndex index="5" type="array">
                                        <numIndex index="0">LLL:EXT:pb_social/Resources/Private/Language/locallang_db.xlf:flexform.tab.youtube.order.rating</numIndex>
                                        <numIndex index="1">rating</numIndex>
                                    </numIndex>
                                </items>
                                <minitems>1</minitems>
                                <maxitems>1</maxitems>
                                <size>1</size>
                            </config>
                        </TCEforms>
                    </settings.youtubeOrder>

                    <settings.youtubePluginKeyfieldEnabled>
                        <TCEforms>
                            <label>LLL:EXT:pb_social/Resources/Private/Language/locallang_db.xlf:flexform.tab.youtube.youtubePluginKeyfieldEnabled</label>
                            <onChange>reload</onChange>
                            <config>
                                <type>check</type>
                            </config>
                        </TCEforms>
                    </settings.youtubePluginKeyfieldEnabled>
                    <settings.youtubeApikey>
                        <TCEforms>
                            <label>LLL:EXT:pb_social/Resources/Private/Language/locallang_extconf.xlf:youtube.apikey</label>
                            <displayCond>FIELD:settings.youtubePluginKeyfieldEnabled:=:1</displayCond>
                            <config>
                                <type>input</type>
                            </config>
                        </TCEforms>
                    </settings.youtubeApikey>
                    
                </el>
            </ROOT>
        </display_youtube>
        <display_vimeo>
            <ROOT>
                <TCEforms>
                    <sheetTitle>LLL:EXT:pb_social/Resources/Private/Language/locallang_db.xlf:flexform.tab.vimeo.caption</sheetTitle>
                </TCEforms>
                <type>array</type>
                <el>
                    <settings.vimeoEnabled>
                        <TCEforms>
                            <label>LLL:EXT:pb_social/Resources/Private/Language/locallang_db.xlf:flexform.tab.vimeo.active</label>
                            <config>
                                <type>check</type>
                            </config>
                        </TCEforms>
                    </settings.vimeoEnabled>
                    
                    <settings.vimeoChannel>
                        <TCEforms>
                            <label>LLL:EXT:pb_social/Resources/Private/Language/locallang_db.xlf:flexform.tab.vimeo.channel</label>
                            <config>
                                <type>input</type>
                            </config>
                        </TCEforms>
                    </settings.vimeoChannel>

                    <settings.vimeoPluginKeyfieldEnabled>
                        <TCEforms>
                            <label>LLL:EXT:pb_social/Resources/Private/Language/locallang_db.xlf:flexform.tab.vimeo.vimeoPluginKeyfieldEnabled</label>
                            <onChange>reload</onChange>
                            <config>
                                <type>check</type>
                            </config>
                        </TCEforms>
                    </settings.vimeoPluginKeyfieldEnabled>
                    <settings.vimeoClientIdentifier>
                        <TCEforms>
                            <label>LLL:EXT:pb_social/Resources/Private/Language/locallang_extconf.xlf:vimeo.client.identifier</label>
                            <displayCond>FIELD:settings.vimeoPluginKeyfieldEnabled:=:1</displayCond>
                            <config>
                                <type>input</type>
                            </config>
                        </TCEforms>
                    </settings.vimeoClientIdentifier>
                    <settings.vimeoClientSecret>
                        <TCEforms>
                            <label>LLL:EXT:pb_social/Resources/Private/Language/locallang_extconf.xlf:vimeo.client.secret</label>
                            <displayCond>FIELD:settings.vimeoPluginKeyfieldEnabled:=:1</displayCond>
                            <config>
                                <type>input</type>
                            </config>
                        </TCEforms>
                    </settings.vimeoClientSecret>
                    <settings.vimeoToken>
                        <TCEforms>
                            <label>LLL:EXT:pb_social/Resources/Private/Language/locallang_extconf.xlf:vimeo.token</label>
                            <displayCond>FIELD:settings.vimeoPluginKeyfieldEnabled:=:1</displayCond>
                            <config>
                                <type>input</type>
                            </config>
                        </TCEforms>
                    </settings.vimeoToken>

                </el>
            </ROOT>
        </display_vimeo>
        <display_tumblr>
            <ROOT>
                <TCEforms>
                    <sheetTitle>LLL:EXT:pb_social/Resources/Private/Language/locallang_db.xlf:flexform.tab.tumblr.caption</sheetTitle>
                </TCEforms>
                <type>array</type>
                <el>
                    <settings.tumblrEnabled>
                        <TCEforms>
                            <label>LLL:EXT:pb_social/Resources/Private/Language/locallang_db.xlf:flexform.tab.tumblr.active</label>

                            <config>
                                <type>check</type>
                            </config>
                        </TCEforms>
                    </settings.tumblrEnabled>
                    <settings.tumblrShowOnlyImages>
                        <TCEforms>
                            <label>LLL:EXT:pb_social/Resources/Private/Language/locallang_db.xlf:flexform.tab.tumblr.showOnlyImages</label>
                            <config>
                                <type>check</type>
                            </config>
                        </TCEforms>
                    </settings.tumblrShowOnlyImages>
                    <settings.tumblrBlogNames>
                        <TCEforms>
                            <label>LLL:EXT:pb_social/Resources/Private/Language/locallang_db.xlf:flexform.tab.tumblr.searchID</label>
                            <config>
                                <type>input</type>
                            </config>
                        </TCEforms>
                    </settings.tumblrBlogNames>
                    <settings.tumblrHashTag>
                        <TCEforms>
                            <label>LLL:EXT:pb_social/Resources/Private/Language/locallang_db.xlf:flexform.tab.tumblr.hashTag</label>
                            <config>
                                <type>input</type>
                            </config>
                        </TCEforms>
                    </settings.tumblrHashTag>

                    <settings.tumblrPluginKeyfieldEnabled>
                        <TCEforms>
                            <label>LLL:EXT:pb_social/Resources/Private/Language/locallang_db.xlf:flexform.tab.tumblr.tumblrPluginKeyfieldEnabled</label>
                            <onChange>reload</onChange>
                            <config>
                                <type>check</type>
                            </config>
                        </TCEforms>
                    </settings.tumblrPluginKeyfieldEnabled>
                    <settings.tumblrConsumerKey>
                        <TCEforms>
                            <label>LLL:EXT:pb_social/Resources/Private/Language/locallang_extconf.xlf:tumblr.consumer.key</label>
                            <displayCond>FIELD:settings.tumblrPluginKeyfieldEnabled:=:1</displayCond>
                            <config>
                                <type>input</type>
                            </config>
                        </TCEforms>
                    </settings.tumblrConsumerKey>
                    <settings.tumblrConsumerSecret>
                        <TCEforms>
                            <label>LLL:EXT:pb_social/Resources/Private/Language/locallang_extconf.xlf:tumblr.consumer.secret</label>
                            <displayCond>FIELD:settings.tumblrPluginKeyfieldEnabled:=:1</displayCond>
                            <config>
                                <type>input</type>
                            </config>
                        </TCEforms>
                    </settings.tumblrConsumerSecret>
                    <settings.tumblrToken>
                        <TCEforms>
                            <label>LLL:EXT:pb_social/Resources/Private/Language/locallang_extconf.xlf:tumblr.token</label>
                            <displayCond>FIELD:settings.tumblrPluginKeyfieldEnabled:=:1</displayCond>
                            <config>
                                <type>input</type>
                            </config>
                        </TCEforms>
                    </settings.tumblrToken>
                    <settings.tumblrTokenSecret>
                        <TCEforms>
                            <label>LLL:EXT:pb_social/Resources/Private/Language/locallang_extconf.xlf:tumblr.token_secret</label>
                            <displayCond>FIELD:settings.tumblrPluginKeyfieldEnabled:=:1</displayCond>
                            <config>
                                <type>input</type>
                            </config>
                        </TCEforms>
                    </settings.tumblrTokenSecret>

                </el>
            </ROOT>
        </display_tumblr>
        <display_imgur>
            <ROOT>
                <TCEforms>
                    <sheetTitle>LLL:EXT:pb_social/Resources/Private/Language/locallang_db.xlf:flexform.tab.imgur.caption</sheetTitle>
                </TCEforms>
                <type>array</type>
                <el>
                    <settings.imgurEnabled>
                        <TCEforms>
                            <label>LLL:EXT:pb_social/Resources/Private/Language/locallang_db.xlf:flexform.tab.imgur.active</label>
                            <config>
                                <type>check</type>
                            </config>
                        </TCEforms>
                    </settings.imgurEnabled>
                    <settings.imgurTags>
                        <TCEforms>
                            <label>LLL:EXT:pb_social/Resources/Private/Language/locallang_db.xlf:flexform.tab.imgur.tag</label>
                            <config>
                                <type>input</type>
                            </config>
                        </TCEforms>
                    </settings.imgurTags>

                    <settings.imgurPluginKeyfieldEnabled>
                        <TCEforms>
                            <label>LLL:EXT:pb_social/Resources/Private/Language/locallang_db.xlf:flexform.tab.imgur.imgurPluginKeyfieldEnabled</label>
                            <onChange>reload</onChange>
                            <config>
                                <type>check</type>
                            </config>
                        </TCEforms>
                    </settings.imgurPluginKeyfieldEnabled>
                    <settings.imgurClientId>
                        <TCEforms>
                            <label>LLL:EXT:pb_social/Resources/Private/Language/locallang_extconf.xlf:imgur.client.id</label>
                            <displayCond>FIELD:settings.imgurPluginKeyfieldEnabled:=:1</displayCond>
                            <config>
                                <type>input</type>
                            </config>
                        </TCEforms>
                    </settings.imgurClientId>
                    <settings.imgurClientSecret>
                        <TCEforms>
                            <label>LLL:EXT:pb_social/Resources/Private/Language/locallang_extconf.xlf:imgur.client.secret</label>
                            <displayCond>FIELD:settings.imgurPluginKeyfieldEnabled:=:1</displayCond>
                            <config>
                                <type>input</type>
                            </config>
                        </TCEforms>
                    </settings.imgurClientSecret>
                </el>
            </ROOT>
        </display_imgur>
        <display_news>
            <ROOT>
                <TCEforms>
                    <sheetTitle>LLL:EXT:pb_social/Resources/Private/Language/locallang_db.xlf:flexform.tab.news.caption</sheetTitle>
                </TCEforms>
                <type>array</type>
                <el>
                    <settings.newsEnabled>
                        <TCEforms>
                            <label>LLL:EXT:pb_social/Resources/Private/Language/locallang_db.xlf:flexform.tab.news.active</label>
                            <config>
                                <type>check</type>
                            </config>
                        </TCEforms>
                    </settings.newsEnabled>

                    <!-- Category -->
                    <settings.newsCategories>
                        <TCEforms>
                            <label>LLL:EXT:pb_social/Resources/Private/Language/locallang_db.xlf:flexform.tab.news.category</label>
                            <config>
                                <type>select</type>
                                <renderMode>tree</renderMode>
                                <renderType>selectTree</renderType>
                                <treeConfig>
                                    <dataProvider>TYPO3\CMS\Core\Tree\TableConfiguration\DatabaseTreeDataProvider</dataProvider>
                                    <parentField>parent</parentField>
                                    <appearance>
                                        <maxLevels>99</maxLevels>
                                        <expandAll>TRUE</expandAll>
                                        <showHeader>TRUE</showHeader>
                                        <width>600</width>
                                    </appearance>
                                </treeConfig>
                                <foreign_table>sys_category</foreign_table>
                                <foreign_table_where>AND (sys_category.sys_language_uid = 0 OR sys_category.l10n_parent = 0) ORDER BY sys_category.sorting</foreign_table_where>
                                <size>15</size>
                                <minitems>0</minitems>
                                <maxitems>99</maxitems>
                            </config>
                        </TCEforms>
                    </settings.newsCategories>

                    <settings.newsDetailPageUid>
                        <TCEforms>
                            <label>LLL:EXT:pb_social/Resources/Private/Language/locallang_db.xlf:flexform.tab.news.newsDetailPageUid</label>
                            <config>
                                <type>group</type>
                                <internal_type>db</internal_type>
                                <allowed>pages</allowed>
                                <size>1</size>
                                <maxitems>1</maxitems>
                                <minitems>0</minitems>
                                <show_thumbs>1</show_thumbs>
                            </config>
                        </TCEforms>
                    </settings.newsDetailPageUid>

                    <settings.useHttpsLinks>
                        <TCEforms>
                            <label>LLL:EXT:pb_social/Resources/Private/Language/locallang_db.xlf:flexform.tab.news.useHttps</label>
                            <config>
                                <type>check</type>
                            </config>
                        </TCEforms>
                    </settings.useHttpsLinks>
                </el>
            </ROOT>
        </display_news>
    </sheets>
</T3DataStructure>